Metadata-Version: 2.1
Name: practica-final-victor
Version: 0.1
Summary: Libreria ejemplo Tema 13
Author: Victor Olivares
Author-email: xxx@gmail.com
License: MIT
Keywords: final,practica
Classifier: Development Status :: 3 - Alpha
Classifier: Intended Audience :: Developers
Classifier: Topic :: Software Development :: Build Tools
Classifier: License :: OSI Approved :: MIT License
Classifier: Programming Language :: Python :: 3
Classifier: Programming Language :: Python :: 3.4
Classifier: Programming Language :: Python :: 3.5
Classifier: Programming Language :: Python :: 3.6
License-File: LICENSE.txt
